slangid/__init__.py
slangid/translator.py
slangid/data/daerah_ke_baku.json
slangid/data/singkatan_ke_baku.json
slangid/data/slang_ke_baku.json
slangid-0.1.0.dist-info/licenses/LICENSE
slangid-0.1.0.dist-info/METADATA
slangid-0.1.0.dist-info/WHEEL
slangid-0.1.0.dist-info/top_level.txt
slangid-0.1.0.dist-info/RECORD
