Metadata-Version: 2.4
Name: slangid
Version: 0.1.0
Summary: Translator slang Indonesia ↔ bahasa formal
Home-page: https://github.com/syukriyansyah-ipb/slang-indonesia
Author: Nama Anda
Author-email: email@anda.com
Classifier: Programming Language :: Python :: 3
Classifier: License :: OSI Approved :: MIT License
Requires-Python: >=3.8
License-File: LICENSE
Dynamic: author
Dynamic: author-email
Dynamic: classifier
Dynamic: description
Dynamic: description-content-type
Dynamic: home-page
Dynamic: license-file
Dynamic: requires-python
Dynamic: summary
